{
  "libros": [
    {
      "titulo": "La inteligencia que asusta",
      "autor": "Mo Gawdat",
      "portada": "https://is1-ssl.mzstatic.com/image/thumb/Publication116/v4/14/03/be/1403be84-1f13-d710-3cd4-3191caf1b234/9788449342141.jpg/626x0w.jpg",
      "tagline": "El futuro de la inteligencia artificial y cómo podemos salvar nuestro mundo",
      "dimension": "Bienestar",
      "punto": "Máximo",
      "palabras": [
        "Esperanza",
        "Innovación",
        "Futuro",
        "Conexión"
      ],
      "frases": [
        "🌟 El futuro brilla con inteligencia positiva. ¡Construyámoslo juntos!",
        "🌈 Imagina un mundo donde la tecnología abraza a la humanidad, ¿cómo sería?",
        "🚀 La esperanza vuela alto, mientras la inteligencia nos guía hacia un mañana mejor. Comparte tu luz, escucha a otros y nunca dejes de aprender.",
        "🌍 La verdadera inteligencia transforma el miedo en oportunidades. Cada elección cuenta."
      ],
      "colores": [
        "#00FF7F",
        "#FFD700",
        "#1E90FF",
        "#FF4500"
      ],
      "fondo": "#11111d",
      "textColors": [
        "#000000",
        "#000000",
        "#FFFFFF",
        "#FFFFFF"
      ],
      "tarjeta": {
        "parrafoTop": "Cada paso que das forma el camino hacia tus metas. La autoconfianza nace de saber que tus decisiones reflejan tus valores.  ",
        "subtitulo": "Define tus prioridades  ",
        "parrafoBot": "Analiza qué es lo que realmente importa para ti. Actuar de acuerdo con esos valores te brindará claridad y propósito en tus acciones.",
        "style": {
          "accent": "#39ff14",
          "ink": "#ffffff",
          "paper": "papel espectral con ondas de color",
          "border": "plata pulida holográfica",
          "serif": "Garamond Nova",
          "sans": "Poppins",
          "marco": "foil iridiscente",
          "fontSizeTitle": "gigante cuántico 50px",
          "fontSizeBody": "susurro etéreo 10–24px",
          "fontWeight": "peso fluctuante 600",
          "lineHeight": "respiración profunda 1.4",
          "letterSpacing": "distancia cósmica +1.5px",
          "textTransform": "mixed",
          "textShadow": "neon astral",
          "layout": "collage fractal",
          "showCover": false,
          "ornamentFlux": "pinceladas efímeras",
          "glitchAura": "halo de fragmentos rotos",
          "dreamGrain": "ruido de ensueño",
          "quantumSpacing": "vacío cuántico +3px",
          "fontWarp": "distorsión gráfica no lineal",
          "animationHint": "breathe espiral",
          "texture": "malla digital vibrante",
          "surprise": "fragmento surrealista de palabra inventada"
        }
      }
    },
    {
      "titulo": "Suficiente",
      "autor": "John C. Bogle",
      "portada": "https://is1-ssl.mzstatic.com/image/thumb/Publication112/v4/3f/c0/bc/3fc0bc78-b53f-721b-34f8-3dad493cb9fb/9788419251077.jpeg/626x0w.jpg",
      "tagline": "Reflexiones sobre el dinero los negocios y la vida",
      "dimension": "Prosperidad",
      "punto": "Máximo",
      "palabras": [
        "Abundancia",
        "Reflexión",
        "Valor",
        "Riqueza"
      ],
      "frases": [
        "💰 La vida es un viaje, no un destino lleno de monedas.",
        "🌱 Lo que siembras hoy en tus finanzas florecerá mañana.",
        "📈 Construye un futuro próspero con pasos firmes y constantes.",
        "🔍 Reflexiona sobre cada centavo, su valor es más profundo de lo que parece."
      ],
      "colores": [
        "#FF7F50",
        "#1E90FF",
        "#FFD700",
        "#8A2BE2"
      ],
      "fondo": "#11111d",
      "textColors": [
        "#000000",
        "#FFFFFF",
        "#000000",
        "#FFFFFF"
      ],
      "tarjeta": {
        "parrafoTop": "A veces nos perdemos en la búsqueda de ganancias rápidas. Es vital enfocarnos en un enfoque de inversión a largo plazo. En \"Suficiente\" de John C. Bogle, la estrategia de invertir de forma constante y con paciencia se vuelve esencial.  ",
        "subtitulo": "Enfoque en el largo plazo  ",
        "parrafoBot": "La clave está en la constancia y en ser disciplinado. Comienza hoy a ahorrar e invertir de manera regular. Hazlo un hábito. Tu futuro financiero dependerá de ello.",
        "style": {
          "accent": "#00ffab",
          "ink": "#0e1a4b",
          "paper": "mar de tinta oscura",
          "border": "reflejo metálico cósmico",
          "serif": "Bodoni XT",
          "sans": "Varela Round",
          "marco": "foil reflejado",
          "fontSizeTitle": "gigante titánico 50px",
          "fontSizeBody": "susurro cósmico 14–36px",
          "fontWeight": "peso celestial 700",
          "lineHeight": "respiración en espiral 1.8",
          "letterSpacing": "expansión cuántica +3px",
          "textTransform": "mixed",
          "textShadow": "neón vibrante",
          "layout": "collage caótico",
          "showCover": false,
          "ornamentFlux": "estallido de pixels dislocados",
          "glowAura": "halo de luz galáctica",
          "dreamGrain": "textura de sueño etéreo",
          "quantumSpacing": "intervalo impredecible 5px",
          "fontFlux": "alteración temporal 18px–150px",
          "animationHint": "vibración de onda cuántica",
          "texture": "tela de estrellas fugaces",
          "surprise": "fragmento abstracto en resplandor"
        }
      }
    },
    {
      "titulo": "Sé tu propio CEO",
      "autor": " Leo Piccioli",
      "portada": "https://is1-ssl.mzstatic.com/image/thumb/Publication211/v4/2c/a4/46/2ca446ef-d5ed-5fa1-309b-410c72c6a93b/1045450739.jpg/626x0w.jpg",
      "tagline": "Hay dos formas de verlo son rebeldes si la empresa quiere aferrarse al pasado. Son líderes si entiende que debe cambiar",
      "dimension": "Prosperidad",
      "punto": "Activo",
      "palabras": [
        "Revolución",
        "Transformación",
        "Empoderamiento",
        "Liderazgo"
      ],
      "frases": [
        "🚀 La verdadera magia sucede cuando se actúa. ",
        "🌈 El cambio florece donde hay valentía. ",
        "🌟 La grandeza empieza desde adentro hacia afuera. ",
        "🔑 Busca la chispa que encienda tu pasión. Tres pasos: despierta tu curiosidad, establece metas valientes y comparte tu viaje."
      ],
      "colores": [
        "#F94D3D",
        "#FCE74E",
        "#0E5C88",
        "#A3D76D"
      ],
      "fondo": "#1A1A1A",
      "textColors": [
        "#FFFFFF",
        "#000000",
        "#FFFFFF",
        "#000000"
      ],
      "tarjeta": {
        "parrafoTop": "Es fundamental tomar las riendas de tu vida y asumir la responsabilidad de tus decisiones. La clave está en actuar con determinación y claridad.  ",
        "subtitulo": "Un paso hacia adelante.  ",
        "parrafoBot": "Evalúa tus objetivos y planifica cómo alcanzarlos. Pregúntate: ¿qué puedo hacer hoy que me acerque a mis metas? Cada pequeña acción suma y define tu futuro.",
        "style": {
          "accent": "#3effa8",
          "ink": "#222222",
          "paper": "universo estelar con neblina azul",
          "border": "brillo de aurora boreal",
          "serif": "Bodoni XT",
          "sans": "Noto Sans Display",
          "marco": "corte glitch sutil",
          "fontSizeTitle": "tamaño cósmico 50px",
          "fontSizeBody": "susurro oscuro 14–36px",
          "fontWeight": "peso gravitacional 750",
          "lineHeight": "danza etérea 1.8",
          "letterSpacing": "espacio infinito +4px",
          "textTransform": "mixed",
          "textShadow": "halo azul vibrante",
          "layout": "collage disonante",
          "showCover": false,
          "ornamentFlux": "efecto de espiral dorada",
          "glowFlux": "destello esmeralda pulsante",
          "quantumSpacing": "distorsión cuántica 3px",
          "dreamGrain": "textura de sueño etéreo",
          "holoInk": "tinta líquida con profundidad dimensional",
          "animationHint": "destello intermitente",
          "metaShadow": "sombra cromática desvanecida",
          "fractureWeight": "peso fractal mínimo 400",
          "surprise": "fragmento ilusorio en texto sin fin"
        }
      }
    },
    {
      "titulo": "Cómo aprender la excelencia",
      "autor": "Eric Potterat",
      "portada": "https://is1-ssl.mzstatic.com/image/thumb/Publication211/v4/bf/6a/b4/bf6ab4c4-4ddb-8110-5ab3-20048dd8d52f/1045367156.jpg/626x0w.jpg",
      "tagline": "Cómo aprender la excelencia nos enseña las habilidades mentales que necesitamos para ser los mejores. Si quieres alcanzar todo tu potencial y más este libro es el lugar perfecto para empezar",
      "dimension": "Bienestar",
      "punto": "Máximo",
      "palabras": [
        "potencial",
        "crecimiento",
        "fuerza",
        "éxito"
      ],
      "frases": [
        "🚀 ¡El cielo es el límite cuando se busca crecer!",
        "🌟 Las habilidades son como flores: si se cuidan, florecen.",
        "💪 Cultivar tu mente es sembrar semillas de grandeza.",
        "🌱 Un pequeño esfuerzo diario, y los logros serán gigantescos."
      ],
      "colores": [
        "#FF6B6B",
        "#FFD93D",
        "#6A0572",
        "#42D9F5"
      ],
      "fondo": "#0D0E1B",
      "textColors": [
        "#FFFFFF",
        "#000000",
        "#FFFFFF",
        "#000000"
      ],
      "tarjeta": {
        "parrafoTop": "La búsqueda de la excelencia comienza en ti. Con cada pequeño paso que des, empieza a construir tu propio camino.  ",
        "subtitulo": "Da el primer paso  ",
        "parrafoBot": "La clave está en actuar hoy. Pregúntate: ¿qué hábito o decisión me acerca a mis objetivos? Hazlo sin miedo, ese primer movimiento te llevará hacia el cambio que buscas.",
        "style": {
          "accent": "#f93f00",
          "ink": "#1c1c1c",
          "paper": "espectro etéreo azul",
          "border": "fractal de luz pulsante",
          "serif": "Bodoni Moda",
          "sans": "Neutraface",
          "marco": "glitch lines reticulares",
          "fontSizeTitle": "cosmos expansivo 40px",
          "fontSizeBody": "susurro resonante 10–25px",
          "fontWeight": "peso onírico 800",
          "lineHeight": "respiración profunda 1.8",
          "letterSpacing": "horizonte de +3px",
          "textTransform": "mixed celestial",
          "textShadow": "holo bruma desvanecida",
          "layout": "collage aleatorio",
          "showCover": false,
          "ornamentFlux": "fragmentos cromáticos desbordados",
          "glowAura": "destello radiante naranja",
          "metaShadow": "sombra en movimiento vibrante",
          "warpGrid": "rejilla distorsionada fractal",
          "prismPulse": "latido arcoíris variable",
          "animationHint": "resplandor nebuloso",
          "texture": "manto de terciopelo cósmico",
          "surprise": "eco de siluetas fluctuantes"
        }
      }
    },
    {
      "titulo": "Sé tu propio CEO",
      "autor": " Leo Piccioli",
      "portada": "https://is1-ssl.mzstatic.com/image/thumb/Publication211/v4/2c/a4/46/2ca446ef-d5ed-5fa1-309b-410c72c6a93b/1045450739.jpg/626x0w.jpg",
      "tagline": "Aprende el método para eliminar automatizar y tercerizar tareas y lidera en la era de la inteligencia artificial",
      "dimension": "Prosperidad",
      "punto": "Activo",
      "palabras": [
        "liderazgo",
        "transformación",
        "eficiencia",
        "creatividad"
      ],
      "frases": [
        "🚀 Liderar es aprender a soltar lo que no importa.",
        "🌱 La creatividad florece cuando las tareas son claras y automáticas.",
        "⚙️ Un buen CEO se enfoca en el futuro, no en el pasado.",
        "📈 Delega lo pequeño y potencia lo grande: una acción al día, inspira a tu equipo."
      ],
      "colores": [
        "#FFC107",
        "#FF3D00",
        "#1E88E5",
        "#4CAF50"
      ],
      "fondo": "#0A0A0A",
      "textColors": [
        "#000000",
        "#FFFFFF",
        "#FFFFFF",
        "#FFFFFF"
      ],
      "tarjeta": {
        "parrafoTop": "Aprender a tomar decisiones es esencial.  ",
        "subtitulo": "¿Estás listo para ser el CEO de tu vida?  ",
        "parrafoBot": "La responsabilidad es la clave para avanzar. Asume el control de tus elecciones, define tus objetivos y toma decisiones alineadas con tu visión. Al hacerlo, no solo avanzarás, sino que también inspirarás a quienes te rodean.",
        "style": {
          "accent": "#32ff7e",
          "ink": "#2c3e50",
          "paper": "bruma dorada intergaláctica",
          "border": "brillo cósmico arcoíris",
          "serif": "Garamond",
          "sans": "Roboto Mono",
          "marco": "foil retro pulsante",
          "fontSizeTitle": "gigante cósmico 50px",
          "fontSizeBody": "susurro etéreo 14–28px",
          "fontWeight": "peso fractal 600",
          "lineHeight": "respiración de nebulosa 1.8",
          "letterSpacing": "intersticio +4px",
          "textTransform": "mixed radical",
          "textShadow": "neón profundo distorsionado",
          "layout": "collage desbordante",
          "showCover": false,
          "ornamentFlux": "fractal líquido impredecible",
          "glowFlux": "brillo jade expansivo",
          "dreamGrain": "grano onírico fluctuante",
          "quantumSpacing": "espaciado cuántico irregular",
          "fontFlux": "variación melódica 10px–150px",
          "animationHint": "respiración intermitente",
          "texture": "malla psicotrópica difusa",
          "surprise": "fragmento etéreo con resonancia múltiple"
        }
      }
    },
    {
      "titulo": "Máxima conexión",
      "autor": "Brad Stulberg",
      "portada": "https://is1-ssl.mzstatic.com/image/thumb/Publication122/v4/7d/4f/9e/7d4f9eb7-8776-fda9-0442-a9c05ad39f0c/1038891568.jpg/626x0w.jpg",
      "tagline": "El éxito promociones premios dinero fallan sistemáticamente en proporcionarnos felicidad duradera Por más trofeos que añadamos a nuestra colección seguimos anhelando algo y sintiéndonos vacíos Groundedness significa poseer una base firme y estable tener un claro sentido del yo gracias al cual podamos encontrar un éxito profundo y duradero en vez de superficial y efímero",
      "dimension": "Conexión",
      "punto": "Máximo",
      "palabras": [
        "Fundamento",
        "Estabilidad",
        "Conexión",
        "Satisfacción"
      ],
      "frases": [
        "🌱 La raíz de la felicidad se encuentra en tu interior.",
        "🎯 Las metas brillantes no son nada sin una base sólida.",
        "🌈 Una vida plena florece con conexión, amor y propósito.",
        "🔑 Cultiva momentos de gratitud, escucha a los demás y respira hondo."
      ],
      "colores": [
        "#6D9DC5",
        "#FFC8D6",
        "#A4D6D4",
        "#F7D07E"
      ],
      "fondo": "#2E2E35",
      "textColors": [
        "#FFFFFF",
        "#000000",
        "#000000",
        "#000000"
      ],
      "tarjeta": {
        "parrafoTop": "Vivir intensamente es un desafío. A menudo nos distraemos y olvidamos lo esencial: estar aquí y ahora.  ",
        "subtitulo": "Simplicidad necesaria  ",
        "parrafoBot": "El libro \"Máxima conexión\" de Brad Stulberg destaca la importancia de sintonizar con nuestras emociones y entorno. En lugar de correr, te animo a que pauses, respires y te centres en lo que verdaderamente importa. Recuerda que la conexión auténtica comienza dentro de ti.",
        "style": {
          "accent": "#00ff8f",
          "ink": "#1b1b1b",
          "paper": "amanecer efervescente con textura de cristal",
          "border": "chrome luminescente",
          "serif": "Bodoni",
          "sans": "Gloock",
          "marco": "glitch dynamique",
          "fontSizeTitle": "max(25px,5vw)",
          "fontSizeBody": "susurro etéreo 14–28px",
          "fontWeight": "peso holográfico 700",
          "lineHeight": "espacio galáctico 1.8",
          "letterSpacing": "desplazamiento etéreo +3px",
          "textTransform": "mixed",
          "textShadow": "blur nebuloso",
          "layout": "collage disruptivo",
          "showCover": false,
          "ornamentFlux": "explosión de trazos irregulares",
          "holoInk": "tinta líquida de auroras",
          "dreamGrain": "nubes oníricas en capas",
          "quantumSpacing": "distancia cuántica inestable",
          "glowAura": "halo vibrante en colores saturados",
          "animationHint": "vibración descontrolada",
          "texture": "sustrato orgánico burbujeante",
          "surprise": "fragmento de palabra con eco fractal"
        }
      }
    },
    {
      "titulo": "Beneath the surface my story",
      "autor": "Michael Phelps",
      "portada": "https://is1-ssl.mzstatic.com/image/thumb/Publication113/v4/51/7d/3e/517d3edd-f3dd-5cc2-3083-65adb9714d86/9781613213247.jpg/626x0w.jpg",
      "tagline": "Prepare to peek into the mind of a champion known as the most decorated Olympian of all time with 28 medals including 23 gold",
      "dimension": "Bienestar",
      "punto": "Máximo",
      "palabras": [
        "superación",
        "dilatación",
        "velocidad",
        "poder"
      ],
      "frases": [
        "🏊‍♂️ La mente de un campeón nunca se detiene.",
        "🌊 En cada ola, un nuevo desafío y un triunfo por descubrir.",
        "🥇 Los sueños se convierten en realidades cuando se nadan con pasión. ¡Inspírate! Considera practicar un nuevo deporte, reflexiona sobre tus metas y comparte tu viaje con alguien especial.",
        "🎖️ A lo largo de su camino, cada medalla simboliza no solo victorias, sino sacrificios y valentía."
      ],
      "colores": [
        "#F9D949",
        "#FF6F61",
        "#1E90FF",
        "#FFD700"
      ],
      "fondo": "#001F3F",
      "textColors": [
        "#000000",
        "#FFFFFF",
        "#FFFFFF",
        "#000000"
      ],
      "tarjeta": {
        "parrafoTop": "El miedo puede paralizarte o impulsarte. El camino de Michael Phelps me recuerda que el verdadero crecimiento ocurre fuera de la zona de confort.  ",
        "subtitulo": "Despierta tu potencial  ",
        "parrafoBot": "El éxito no llega sin esfuerzo. Haz algo que te asuste hoy; ese pequeño paso puede ser el inicio de un cambio monumental.",
        "style": {
          "accent": "#c700ff",
          "ink": "#2f2f2f",
          "paper": "nube de neón con destellos intergalácticos",
          "border": "marco glitch cinético",
          "serif": "Bodoni Modern",
          "sans": "Suisse Int'l",
          "marco": "foil iridiscente",
          "fontSizeTitle": "cósmico colosal 50px",
          "fontSizeBody": "susurro de estrellas 10–28px",
          "fontWeight": "peso cuántico 800",
          "lineHeight": "pulso gravitacional 1.4",
          "letterSpacing": "brecha temporal +3px",
          "textTransform": "lowercase cósmico",
          "textShadow": "neon fraccionado",
          "layout": "collage errático",
          "showCover": false,
          "ornamentFlux": "hilos de luz fragmentada",
          "glowAura": "halo radiante violeta",
          "quantumSpacing": "intersticio espacial 4px",
          "dreamGrain": "ruido de universo alternativo",
          "animationHint": "breathe cuántico",
          "texture": "liquidez cinética metalizada",
          "surprise": "palabra inventada: 'fractaloría'"
        }
      }
    },
    {
      "titulo": "El poder de ser valiosos",
      "autor": "Arnold Schwarzenegger",
      "portada": "https://is1-ssl.mzstatic.com/image/thumb/Publication126/v4/07/b1/c8/07b1c850-e7f0-534b-bad7-d1106aabc300/9788419699893.jpeg/626x0w.jpg",
      "tagline": "Tienes que transformarte en una persona valiosa útil para los demás",
      "dimension": "Conexión",
      "punto": "Máximo",
      "palabras": [
        "brillantez",
        "solidaridad",
        "crecimiento",
        "esperanza"
      ],
      "frases": [
        "💎 Cada vez que ayudas, creas un brillo en el mundo.",
        "🤝 La verdadera fuerza radica en ser útil y apoyar a los demás.",
        "🌱 Cuando compartes, haces que tu corazón crezca como un árbol frondoso.",
        "⭐ Ofrece tu mano, escucha con el corazón, y mira cómo florecen las sonrisas."
      ],
      "colores": [
        "#FF6F61",
        "#6B5B95",
        "#88B04B",
        "#F7CAC9"
      ],
      "fondo": "#2D303A",
      "textColors": [
        "#FFFFFF",
        "#FFFFFF",
        "#000000",
        "#000000"
      ],
      "tarjeta": {
        "parrafoTop": "En un mundo donde la búsqueda de éxito es constante, lo que realmente importa es el valor que le das a tu vida. Este es el mensaje de Arnold Schwarzenegger en \"El poder de ser valiosos\". ",
        "subtitulo": "Puntos de impacto",
        "parrafoBot": "Céntrate en tus habilidades únicas. Cada persona tiene algo valioso que ofrecer. Toma un momento para identificar qué te hace especial y comienza a potenciarlo. Haz de ese talento el motor de tu vida. Actúa. Haz algo hoy que te acerque a desarrollar esa singularidad.",
        "style": {
          "accent": "#0beeff",
          "ink": "#1f1f1f",
          "paper": "papel espectral vibrante",
          "border": "luz violeta cinética",
          "serif": "Bodoni",
          "sans": "Suisse Int'l",
          "marco": "foil reluciente",
          "fontSizeTitle": "gigante cósmico 36–200px",
          "fontSizeBody": "susurro mínimo 10–24px",
          "fontWeight": "peso etéreo 700",
          "lineHeight": "respiración breve 1.2",
          "letterSpacing": "distancia cuántica +4px",
          "textTransform": "title-case extravagante",
          "textShadow": "neón brillante distorsionado",
          "layout": "collage en espiral",
          "showCover": false,
          "ornamentFlux": "doodles fractales ilimitados",
          "glowAura": "resplandor de galaxia azul",
          "quantumSpacing": "intervalos imposibles 3px",
          "fontWarp": "tipografía flotante expansiva",
          "animationHint": "respiración etérea constante",
          "texture": "nebulosa digital brillante",
          "surprise": "fragmentos tipográficos reversibles"
        }
      }
    },
    {
      "titulo": "Aprendiendo de los mejores",
      "autor": "Francisco Alcaide Hernández",
      "portada": "https://is1-ssl.mzstatic.com/image/thumb/Publication128/v4/a4/85/f3/a485f368-f4a3-c28d-da91-3d92222a56a6/9788416928651.jpg/626x0w.jpg",
      "tagline": "libro de cabecera de muchas personas por su capacidad de sintetizar y explicar una ingente cantidad de conocimiento y sabiduría sobre el mundo del desarrollo personal los negocios el liderazgo la libertad financiera o la espiritualidad",
      "dimension": "Conexión",
      "punto": "Máximo",
      "palabras": [
        "sabiduría",
        "crecimiento",
        "inspiración",
        "liderazgo"
      ],
      "frases": [
        "🌟 La libertad es un camino lleno de aprendizaje y magia.",
        "🌱 Crecer es abrazar cada desafío con alegría y pasión.",
        "✨ Cuando uno aprende, toda su vida se ilumina con nuevas oportunidades.",
        "🗝️ Tres maneras de abrir las puertas del conocimiento: Lee un libro hoy, conversa con alguien que admires, escribe tus reflexiones cada mañana."
      ],
      "colores": [
        "#FFC107",
        "#FF5722",
        "#673AB7",
        "#4CAF50"
      ],
      "fondo": "#0D0D0D",
      "textColors": [
        "#000000",
        "#FFFFFF",
        "#FFFFFF",
        "#FFFFFF"
      ],
      "tarjeta": {
        "parrafoTop": "Para alcanzar el éxito, es vital cultivar la autodisciplina en nuestras vidas. Sin ella, nuestras metas se convierten en deseos.  ",
        "subtitulo": "Construyendo hábitos sólidos  ",
        "parrafoBot": "Un enfoque consciente en el día a día nos permite desarrollar esta habilidad. Empieza hoy mismo: elige una acción pequeña y consistente que te acerque a tus objetivos.",
        "style": {
          "accent": "#ff5e2e",
          "ink": "#222222",
          "paper": "viento estelar con texturas de sombra",
          "border": "circuito brillante",
          "serif": "Garamond Luxe",
          "sans": "Futura Wave",
          "marco": "foil holográfico fractal",
          "fontSizeTitle": "gigante cuántico 40–120px",
          "fontSizeBody": "susurro visual 10–28px",
          "fontWeight": "densidad lumínica 850",
          "lineHeight": "respiración fractal 1.4",
          "letterSpacing": "abismo estelar +3px",
          "textTransform": "mixed-oscillation",
          "textShadow": "neon pulsante",
          "layout": "collage surrealista",
          "showCover": false,
          "coverStyle": "pixelated vision",
          "glowFlux": "aura radiante en cascada",
          "ornamentFlux": "rayos de luz cósmica",
          "warpGrid": "repliegue dimensional",
          "dreamGrain": "nube de sueños pixelados",
          "quantumSpacing": "espaciado fluido 1.5",
          "animationHint": "breathe holográfico ondulante",
          "texture": "carta de espuma intergaláctica",
          "surprise": "fragmento dimensional distorsionado"
        }
      }
    },
    {
      "titulo": "Objections",
      "autor": "Jeb Blount",
      "portada": "https://is1-ssl.mzstatic.com/image/thumb/Publication115/v4/e3/81/ef/e381ef86-1d0d-3def-e0cb-5fe25748b832/9781119477372.jpg/626x0w.jpg",
      "tagline": "you ll learn a new psychology for turning-around objections and proven techniques that work with todays more informed in control and skeptical buyers",
      "dimension": "Prosperidad",
      "punto": "Máximo",
      "palabras": [
        "Convicción",
        "Persuasión",
        "Crecimiento",
        "Impacto"
      ],
      "frases": [
        "🔍 La curiosidad transforma el rechazo en oportunidad.",
        "🛠️ La estrategia es la llave que abre corazones y mentes.",
        "🚀 En cada objeción hay un camino hacia el entendimiento. Recuerda, pregunta, escucha.",
        "📝 Siente la confianza de dar pasos claros hacia el éxito. Mira cómo las objeciones se convierten en aliados."
      ],
      "colores": [
        "#FF6F61",
        "#6B5B93",
        "#88B04B",
        "#F7CAC9"
      ],
      "fondo": "#2C3E50",
      "textColors": [
        "#FFFFFF",
        "#FFFFFF",
        "#000000",
        "#000000"
      ],
      "tarjeta": {
        "parrafoTop": "Es crucial aprender a ver las objeciones como un espacio para profundizar.  ",
        "subtitulo": "Aprovecha cada rechazo.  ",
        "parrafoBot": "Con la mentalidad adecuada, cada no puede acercarte más al sí que buscas. No evites las objeciones, enfócate en desmantelarlas y construir confianza en el proceso.",
        "style": {
          "accent": "#1abc9c",
          "ink": "#ecf0f1",
          "paper": "neblina estelar",
          "border": "oro viejo iridiscente",
          "serif": "Bodoni XT",
          "sans": "Exo 2",
          "marco": "cutout estelar",
          "fontSizeTitle": "cosmic gigantic 50px",
          "fontSizeBody": "susurro vibrante 14–28px",
          "fontWeight": "peso fractal 700",
          "lineHeight": "respiración poética 1.4",
          "letterSpacing": "abismo profundo +3px",
          "textTransform": "mixed liquid",
          "textShadow": "glow vibrante 3px 3px",
          "layout": "collage abstracto",
          "showCover": false,
          "ornamentFlux": "líneas de glitching en oro",
          "holoInk": "tinta cromática fluctuante",
          "quantumSpacing": "espaciado cuántico 0.1em",
          "dreamGrain": "grano de sueño onírico",
          "animationHint": "breathe surrealismo",
          "fractalPulse": "pulsación fractal de luz",
          "surprise": "palabra inventada: fractalocéntrico"
        }
      }
    }
  ]
}